argsubparse/__init__.py
argsubparse/argsubparse.py
argsubparse-0.0.13.dist-info/LICENSE
argsubparse-0.0.13.dist-info/METADATA
argsubparse-0.0.13.dist-info/WHEEL
argsubparse-0.0.13.dist-info/top_level.txt
argsubparse-0.0.13.dist-info/RECORD
